ixapipes/IxaPipesModule.py
ixapipes/__init__.py
ixapipes/models.py
ixapipes/pos.py
ixapipes/tok.py
ixapipes/utils.py
ixapipes-0.0.6.dist-info/LICENSE.md
ixapipes-0.0.6.dist-info/METADATA
ixapipes-0.0.6.dist-info/WHEEL
ixapipes-0.0.6.dist-info/top_level.txt
ixapipes-0.0.6.dist-info/RECORD
