Metadata-Version: 2.1
Name: ixapipes
Version: 0.0.6
Summary: Python bindings for Ixa Pipes
Home-page: https://github.com/ikergarcia1996/Python-IXA-Pipes
Author: Iker García Ferrero
Author-email: iker.garciaf@ehu.eus
License: UNKNOWN
Project-URL: Bug Tracker, https://github.com/ikergarcia1996/Python-IXA-Pipes/issues
Platform: UNKNOWN
Classifier: Programming Language :: Python :: 3
Classifier: License :: OSI Approved :: Apache Software License
Classifier: Operating System :: POSIX :: Linux
Requires-Python: >=3.6
